Bayes/__init__.py
Bayes/try.py
Bayes/examples/__init__.py
Bayes/examples/california_housing_regression.py
Bayes/examples/toy_regression.py
Bayes/losses/__init__.py
Bayes/losses/kl_divergence.py
Bayes/models/__init__.py
Bayes/models/regression.py
Bayes/modules/__init__.py
Bayes/modules/base_bayesian_module.py
Bayes/modules/linear_bayesian_layer.py
Bayes/modules/weight_sampler.py
Bayes/utils/__init__.py
Bayes/utils/data_utils.py
Bayes/utils/regression_trainer.py
Bayes/utils/variational_estimator.py
bayes_regression-0.1.7.dist-info/LICENSE
bayes_regression-0.1.7.dist-info/METADATA
bayes_regression-0.1.7.dist-info/WHEEL
bayes_regression-0.1.7.dist-info/top_level.txt
bayes_regression-0.1.7.dist-info/RECORD
