Metadata-Version: 2.2
Name: bayes-regression
Version: 0.1.7
Summary: A Bayesian Neural Network framework for regression tasks implemented in PyTorch.
Home-page: https://github.com/zchccsx/Bayes-by-Backprop
Author: Chenhang Zheng
Author-email: chenhang.zheng.edu@outlook.com
Requires-Python: >=3.8
License-File: LICENSE
Dynamic: author
Dynamic: author-email
Dynamic: description
Dynamic: description-content-type
Dynamic: home-page
Dynamic: requires-python
Dynamic: summary
